trp/__init__.py
trp/__version__.py
textract_trp-0.1.2.dist-info/WHEEL
textract_trp-0.1.2.dist-info/METADATA
textract_trp-0.1.2.dist-info/RECORD
